jsonchain/__init__.py
jsonchain/envelope.py
jsonchain/io.py
jsonchain/tables.py
jsonchain/tree.py
jsonchain-0.5.1.dist-info/entry_points.txt
jsonchain-0.5.1.dist-info/licenses/LICENSE
jsonchain-0.5.1.dist-info/WHEEL
jsonchain-0.5.1.dist-info/METADATA
jsonchain-0.5.1.dist-info/RECORD
